flarecast/__init__.py
flarecast/service/__init__.py
flarecast/service/flarecast_service.py
flarecast/service/mini_json_encoder.py
flarecast/service/service_response.py
flarecast_service-0.1.0.265.dist-info/DESCRIPTION.rst
flarecast_service-0.1.0.265.dist-info/METADATA
flarecast_service-0.1.0.265.dist-info/RECORD
flarecast_service-0.1.0.265.dist-info/WHEEL
flarecast_service-0.1.0.265.dist-info/metadata.json
flarecast_service-0.1.0.265.dist-info/top_level.txt
