Metadata-Version: 2.0
Name: flarecast-service
Version: 0.1.0.265
Summary: Flarecast Service is the base package of all flarecast connexion services.
Home-page: https://dev.flarecast.eu/stash/projects/INFRA/repos/flarecastservice/
Author: i4Ds
Author-email: florian.bruggisser@fhnw.ch
License: UNKNOWN
Download-URL: https://dev.flarecast.eu/stash/scm/infra/flarecastservice.git
Keywords: flarecast,service,web,connexion,base,i4Ds
Platform: UNKNOWN
Classifier: Programming Language :: Python
Classifier: Programming Language :: Python :: 2.7
Classifier: Development Status :: 4 - Beta
Classifier: Intended Audience :: Developers
Classifier: Operating System :: OS Independent
Requires-Dist: Flask-Compress
Requires-Dist: Flask-Cors
Requires-Dist: connexion
